dug/__init__.py
dug/annotate.py
dug/api.py
dug/config.py
dug/core.py
dug/parsers.py
dug/tranql.py
dug/utils.py
dug_test-1.0.13.dist-info/LICENSE
dug_test-1.0.13.dist-info/METADATA
dug_test-1.0.13.dist-info/WHEEL
dug_test-1.0.13.dist-info/top_level.txt
dug_test-1.0.13.dist-info/RECORD
