Metadata-Version: 2.1
Name: dug-test
Version: 1.0.13
Summary: Dug is a semantic searching and indexing software.
Home-page: https://github.com/helxplatform/dug.git
Maintainer: 
Maintainer-email: 
License: UNKNOWN
Platform: UNKNOWN
Classifier: Programming Language :: Python :: 3
Classifier: License :: OSI Approved :: MIT License
Classifier: Operating System :: OS Independent
Requires-Python: >=3.7
Requires-Dist: alabaster (==0.7.12)
Requires-Dist: aniso8601 (==8.0.0)
Requires-Dist: antlr4-python3-runtime (==4.9)
Requires-Dist: appnope (==0.1.0)
Requires-Dist: attrs (==19.3.0)
Requires-Dist: Babel (==2.8.0)
Requires-Dist: backcall (==0.1.0)
Requires-Dist: biolinkml (==1.4.9)
Requires-Dist: bleach (==3.1.1)
Requires-Dist: cachetools (==4.0.0)
Requires-Dist: certifi (==2019.11.28)
Requires-Dist: CFGraph (==0.2.1)
Requires-Dist: chardet (==3.0.4)
Requires-Dist: click (==7.1.1)
Requires-Dist: decorator (==4.4.2)
Requires-Dist: defusedxml (==0.6.0)
Requires-Dist: docutils (==0.16)
Requires-Dist: elasticsearch (==7.5.1)
Requires-Dist: elasticsearch-dsl (==7.1.0)
Requires-Dist: entrypoints (==0.3)
Requires-Dist: flasgger (==0.9.4)
Requires-Dist: Flask (==1.1.1)
Requires-Dist: Flask-Cors (==3.0.8)
Requires-Dist: Flask-RESTful (==0.3.8)
Requires-Dist: graphviz (==0.13.2)
Requires-Dist: gunicorn (==20.0.4)
Requires-Dist: idna (==2.8)
Requires-Dist: imagesize (==1.2.0)
Requires-Dist: importlib-metadata (==1.5.0)
Requires-Dist: incremental (==17.5.0)
Requires-Dist: ipykernel (==5.1.4)
Requires-Dist: ipython (==7.13.0)
Requires-Dist: ipython-genutils (==0.2.0)
Requires-Dist: ipywidgets (==7.5.1)
Requires-Dist: isodate (==0.6.0)
Requires-Dist: itsdangerous (==1.1.0)
Requires-Dist: jedi (==0.16.0)
Requires-Dist: Jinja2 (==2.11.1)
Requires-Dist: jsonasobj (==1.2.1)
Requires-Dist: jsonschema (==3.2.0)
Requires-Dist: jupyter (==1.0.0)
Requires-Dist: jupyter-client (==6.0.0)
Requires-Dist: jupyter-console (==6.1.0)
Requires-Dist: jupyter-core (==4.6.3)
Requires-Dist: MarkupSafe (==1.1.1)
Requires-Dist: mistune (==0.8.4)
Requires-Dist: more-itertools (==8.2.0)
Requires-Dist: mypy (==0.770)
Requires-Dist: mypy-extensions (==0.4.3)
Requires-Dist: nbconvert (==5.6.1)
Requires-Dist: nbformat (==5.0.4)
Requires-Dist: neo4j (==1.7.6)
Requires-Dist: neo4jrestclient (==2.1.1)
Requires-Dist: neobolt (==1.7.16)
Requires-Dist: neotime (==1.7.4)
Requires-Dist: networkx (==2.4)
Requires-Dist: notebook (==6.0.3)
Requires-Dist: numpy (==1.18.1)
Requires-Dist: ordered-set (==4.0.2)
Requires-Dist: packaging (==20.3)
Requires-Dist: pandas (==1.0.1)
Requires-Dist: pandocfilters (==1.4.2)
Requires-Dist: parso (==0.6.2)
Requires-Dist: pbr (==5.4.4)
Requires-Dist: pexpect (==4.8.0)
Requires-Dist: pickleshare (==0.7.5)
Requires-Dist: pip-check-reqs (==2.0.3)
Requires-Dist: pluggy (==0.13.1)
Requires-Dist: prefixcommons (==0.1.9)
Requires-Dist: prologterms (==0.0.6)
Requires-Dist: prometheus-client (==0.7.1)
Requires-Dist: prompt-toolkit (==3.0.4)
Requires-Dist: ptyprocess (==0.6.0)
Requires-Dist: py (==1.8.1)
Requires-Dist: Pygments (==2.6.1)
Requires-Dist: PyJSG (==0.11.6)
Requires-Dist: pyparsing (==2.4.6)
Requires-Dist: pyrsistent (==0.15.7)
Requires-Dist: PyShEx (==0.7.14)
Requires-Dist: PyShExC (==0.8.2)
Requires-Dist: pystache (==0.5.4)
Requires-Dist: pytest (==5.4.0)
Requires-Dist: python-dateutil (==2.8.1)
Requires-Dist: python-Levenshtein (==0.12.0)
Requires-Dist: pytz (==2019.3)
Requires-Dist: PyYAML (==5.3)
Requires-Dist: pyzmq (==19.0.0)
Requires-Dist: qtconsole (==4.7.1)
Requires-Dist: QtPy (==1.9.0)
Requires-Dist: rdflib (==5.0.0)
Requires-Dist: rdflib-jsonld (==0.5.0)
Requires-Dist: redis (==3.4.1)
Requires-Dist: requests (==2.22.0)
Requires-Dist: requests-cache (==0.5.2)
Requires-Dist: Send2Trash (==1.5.0)
Requires-Dist: ShExJSG (==0.7.1)
Requires-Dist: six (==1.14.0)
Requires-Dist: snowballstemmer (==2.0.0)
Requires-Dist: sparql-slurper (==0.3.3)
Requires-Dist: SPARQLWrapper (==1.8.5)
Requires-Dist: Sphinx (==2.4.4)
Requires-Dist: sphinx-click (==2.3.1)
Requires-Dist: sphinx-rtd-theme (==0.4.3)
Requires-Dist: sphinxcontrib-applehelp (==1.0.2)
Requires-Dist: sphinxcontrib-devhelp (==1.0.2)
Requires-Dist: sphinxcontrib-htmlhelp (==1.0.3)
Requires-Dist: sphinxcontrib-jsmath (==1.0.1)
Requires-Dist: sphinxcontrib-qthelp (==1.0.3)
Requires-Dist: sphinxcontrib-serializinghtml (==1.1.4)
Requires-Dist: stringcase (==1.2.0)
Requires-Dist: terminado (==0.8.3)
Requires-Dist: terminaltables (==3.1.0)
Requires-Dist: testpath (==0.4.4)
Requires-Dist: tornado (==6.0.4)
Requires-Dist: traitlets (==4.3.3)
Requires-Dist: typed-ast (==1.4.1)
Requires-Dist: typing-extensions (==3.7.4.1)
Requires-Dist: urllib3 (==1.25.7)
Requires-Dist: validators (==0.14.2)
Requires-Dist: wcwidth (==0.1.8)
Requires-Dist: webencodings (==0.5.1)
Requires-Dist: Werkzeug (==0.16.1)
Requires-Dist: widgetsnbextension (==3.5.1)
Requires-Dist: zipp (==3.1.0)
Requires-Dist: jsonlines (>=1.2.0)
